ssh/__init__.pxd
ssh/__init__.py
ssh/_version.py
ssh/c_callbacks.pxd
ssh/c_legacy.pxd
ssh/c_sftp.pxd
ssh/c_ssh.pxd
ssh/c_ssh2.pxd
ssh/callbacks.cpython-39-aarch64-linux-gnu.so
ssh/callbacks.pxd
ssh/channel.cpython-39-aarch64-linux-gnu.so
ssh/channel.pxd
ssh/connector.cpython-39-aarch64-linux-gnu.so
ssh/connector.pxd
ssh/error_codes.cpython-39-aarch64-linux-gnu.so
ssh/event.cpython-39-aarch64-linux-gnu.so
ssh/event.pxd
ssh/exceptions.cpython-39-aarch64-linux-gnu.so
ssh/key.cpython-39-aarch64-linux-gnu.so
ssh/key.pxd
ssh/keytypes.cpython-39-aarch64-linux-gnu.so
ssh/keytypes.pxd
ssh/options.cpython-39-aarch64-linux-gnu.so
ssh/options.pxd
ssh/scp.cpython-39-aarch64-linux-gnu.so
ssh/scp.pxd
ssh/session.cpython-39-aarch64-linux-gnu.so
ssh/session.pxd
ssh/sftp.cpython-39-aarch64-linux-gnu.so
ssh/sftp.pxd
ssh/sftp_attributes.cpython-39-aarch64-linux-gnu.so
ssh/sftp_attributes.pxd
ssh/sftp_handles.cpython-39-aarch64-linux-gnu.so
ssh/sftp_handles.pxd
ssh/sftp_statvfs.cpython-39-aarch64-linux-gnu.so
ssh/sftp_statvfs.pxd
ssh/utils.cpython-39-aarch64-linux-gnu.so
ssh/utils.pxd
ssh_python.libs/libcom_err-d5c1099c.so.3.0
ssh_python.libs/libcrypto-b84b85b2.so.3
ssh_python.libs/libgssapi_krb5-760eb76e.so.2.2
ssh_python.libs/libk5crypto-96a9d9bb.so.3.1
ssh_python.libs/libkrb5-6122b5e6.so.3.3
ssh_python.libs/libkrb5support-782b6275.so.0.1
ssh_python.libs/libssh-daef26e7.so.4.10.3
ssh_python-1.2.0.post1.dist-info/METADATA
ssh_python-1.2.0.post1.dist-info/WHEEL
ssh_python-1.2.0.post1.dist-info/top_level.txt
ssh_python-1.2.0.post1.dist-info/RECORD
ssh_python-1.2.0.post1.dist-info/licenses/COPYING
ssh_python-1.2.0.post1.dist-info/licenses/LICENSE
